ptwrkshpbasecode/__init__.py
ptwrkshpbasecode/client/__init__.py
ptwrkshpbasecode/client/ptwrkshpclient.py
ptwrkshpbasecode/server/__init__.py
ptwrkshpbasecode/server/ptwrkshpserver.py
ptwrkshpbasecode-0.0.2.dist-info/METADATA
ptwrkshpbasecode-0.0.2.dist-info/WHEEL
ptwrkshpbasecode-0.0.2.dist-info/entry_points.txt
ptwrkshpbasecode-0.0.2.dist-info/top_level.txt
ptwrkshpbasecode-0.0.2.dist-info/RECORD
